{
  "@type": ".Game",
  "id": "vinnare_2026-05-01_24_2",
  "status": "bettable",
  "pools": {
    "vinnare": {
      "@type": ".VinnarePool",
      "id": "vinnare_2026-05-01_24_2",
      "status": "bettable",
      "timestamp": "2026-05-01 18:35:15",
      "turnover": 5845500,
      "betType": "vinnare"
    }
  },
  "races": [
    {
      "id": "2026-05-01_24_2",
      "date": "2026-05-01",
      "number": 2,
      "distance": 2140,
      "startMethod": "volte",
      "startTime": "2026-05-01T18:42:00",
      "scheduledStartTime": "2026-05-01T18:42:00",
      "prize": "Pris: 12.000-7.000-5.000-4.000-3.000-2.500-2.300-2.300 kr (8 prisplacerade). L\u00e4gst 1.500 kr till alla t\u00e4vlande. Prispengar max total: 48.600 kr.",
      "terms": [
        "3-\u00e5riga och \u00e4ldre 60.001 - 180.000 kr med h\u00f6gst 1000 po\u00e4ng. K\u00f6rsvenskrav kat. 2. K\u00f6rsvenner f\u00f6dda 080501 eller tidigare.",
        "Hederspris till segrande h\u00e4sts \u00e4gare.",
        "2140 m. Till\u00e4gg 20 m vid 401 po\u00e4ng."
      ],
      "sport": "trot",
      "track": {
        "id": 24,
        "name": "R\u00e4ttvik",
        "countryCode": "SE",
        "sportSystemCode": "R\u00c4"
      },
      "status": "upcoming",
      "nextRace": true,
      "pools": {
        "vinnare": {
          "@type": ".VinnarePool",
          "id": "vinnare_2026-05-01_24_2",
          "status": "bettable",
          "timestamp": "2026-05-01 18:35:15",
          "turnover": 5845500,
          "betType": "vinnare"
        },
        "plats": {
          "@type": ".PlatsPool",
          "id": "plats_2026-05-01_24_2",
          "status": "bettable",
          "timestamp": "2026-05-01 18:35:15",
          "turnover": 5845500,
          "betType": "plats"
        }
      },
      "starts": [
        {
          "id": "2026-05-01_24_2_1",
          "number": 1,
          "postPosition": 1,
          "distance": 2140,
          "horse": {
            "id": 759966,
            "name": "Pointless Dream",
            "age": 9,
            "sex": "mare",
            "record": {
              "code": "K",
              "startMethod": "volte",
              "distance": "short",
              "time": {
                "minutes": 1,
                "seconds": 15,
                "tenths": 7
              }
            },
            "trainer": {
              "id": 193430,
              "firstName": "Johan",
              "lastName": "Sandstr\u00f6m",
              "shortName": "San Jo",
              "location": "Falun",
              "birth": 1980,
              "homeTrack": {
                "id": 23,
                "name": "Romme"
              },
              "license": "B-tr\u00e4nare: tr\u00e4na, k\u00f6ra f\u00f6r bolag",
              "silks": "Gr\u00f6n,vitt axelp m gr stj,gr\u00f6n rev;vit",
              "statistics": {
                "years": {
                  "2025": {
                    "starts": 27,
                    "earnings": 7950000,
                    "placement": {
                      "3": 2,
                      "2": 1,
                      "1": 0
                    },
                    "winPercentage": 0
                  },
                  "2026": {
                    "starts": 2,
                    "earnings": 450000,
                    "placement": {
                      "3": 0,
                      "2": 0,
                      "1": 0
                    },
                    "winPercentage": 0
                  }
                }
              }
            },
            "shoes": {
              "reported": true,
              "front": {
                "hasShoe": true,
                "changed": false
              },
              "back": {
                "hasShoe": true,
                "changed": false
              }
            },
            "sulky": {
              "reported": true,
              "type": {
                "code": "VA",
                "text": "Vanlig",
                "engText": "Standard",
                "changed": false
              },
              "colour": {
                "code": "GU",
                "text": "Gul",
                "engText": "Yellow",
                "changed": false
              }
            },
            "money": 157400,
            "color": "m\u00f6rkbrun",
            "homeTrack": {
              "id": 23,
              "name": "Romme"
            },
            "owner": {
              "id": 561539,
              "name": "Sandstr\u00f6m J, C & L, Hessman T"
            },
            "breeder": {
              "id": 568022,
              "name": "Sandstr\u00f6m Johan & Hessman Tobias"
            },
            "statistics": {
              "years": {
                "2025": {
                  "starts": 13,
                  "earnings": 3580000,
                  "placement": {
                    "3": 1,
                    "2": 0,
                    "1": 0
                  },
                  "records": [
                    {
                      "code": "aK",
                      "startMethod": "auto",
                      "distance": "short",
                      "time": {
                        "minutes": 1,
                        "seconds": 16,
                        "tenths": 0
                      },
                      "place": 8
                    },
                    {
                      "code": "K",
                      "startMethod": "volte",
                      "distance": "short",
                      "time": {
                        "minutes": 1,
                        "seconds": 15,
                        "tenths": 7
                      },
                      "place": 8
                    }
                  ]
                },
                "2026": {
                  "starts": 1,
                  "earnings": 300000,
                  "placement": {
                    "3": 0,
                    "2": 0,
                    "1": 0
                  },
                  "records": [
                    {
                      "code": "M",
                      "startMethod": "volte",
                      "distance": "medium",
                      "time": {
                        "minutes": 1,
                        "seconds": 16,
                        "tenths": 2
                      },
                      "place": 5
                    }
                  ]
                }
              },
              "life": {
                "starts": 46,
                "earnings": 15740000,
                "placement": {
                  "3": 4,
                  "2": 0,
                  "1": 1
                },
                "records": [
                  {
                    "code": "aK",
                    "startMethod": "auto",
                    "distance": "short",
                    "time": {
                      "minutes": 1,
                      "seconds": 16,
                      "tenths": 0
                    },
                    "place": 8,
                    "year": "2025"
                  },
                  {
                    "code": "aM",
                    "startMethod": "auto",
                    "distance": "medium",
                    "time": {
                      "minutes": 1,
                      "seconds": 16,
                      "tenths": 2
                    },
                    "place": 3,
                    "year": "2025"
                  },
                  {
                    "code": "K",
                    "startMethod": "volte",
                    "distance": "short",
                    "time": {
                      "minutes": 1,
                      "seconds": 15,
                      "tenths": 7
                    },
                    "place": 8,
                    "year": "2025"
                  },
                  {
                    "code": "M",
                    "startMethod": "volte",
                    "distance": "medium",
                    "time": {
                      "minutes": 1,
                      "seconds": 16,
                      "tenths": 2
                    },
                    "place": 5,
                    "year": "2026"
                  },
                  {
                    "code": "L",
                    "startMethod": "volte",
                    "distance": "long",
                    "time": {
                      "minutes": 1,
                      "seconds": 18,
                      "tenths": 3
                    },
                    "place": 0,
                    "year": "2023"
                  }
                ],
                "winPercentage": 217,
                "placePercentage": 1086,
                "earningsPerStart": 342173,
                "startPoints": 333
              },
              "lastFiveStarts": {
                "averageOdds": 7659
              }
            },
            "pedigree": {
              "father": {
                "id": 703365,
                "name": "Pojke Kronos",
                "nationality": "IT"
              },
              "mother": {
                "id": 515561,
                "name": "Noblesse Rivner"
              },
              "grandfather": {
                "id": 2456,
                "name": "Alf Palema",
                "nationality": "US"
              }
            }
          },
          "driver": {
            "id": 86308,
            "firstName": "Kajsa",
            "lastName": "Frick",
            "shortName": "Fri Ka",
            "location": "Vikarbyn",
            "birth": 1976,
            "homeTrack": {
              "id": 24,
              "name": "R\u00e4ttvik"
            },
            "license": "A-tr\u00e4nare: tr\u00e4na, k\u00f6ra",
            "silks": "Bl\u00e5/vit, diagonalt delad, rev\u00e4r; bl\u00e5",
            "statistics": {
              "years": {
                "2025": {
                  "starts": 324,
                  "earnings": 218010000,
                  "placement": {
                    "3": 38,
                    "2": 22,
                    "1": 14
                  },
                  "winPercentage": 432
                },
                "2026": {
                  "starts": 104,
                  "earnings": 87070000,
                  "placement": {
                    "3": 7,
                    "2": 9,
                    "1": 11
                  },
                  "winPercentage": 1057
                }
              }
            }
          },
          "pools": {
            "vinnare": {
              "@type": ".VinnareStartPool",
              "odds": 1162
            },
            "plats": {
              "@type": ".PlatsStartPool",
              "minOdds": 211,
              "maxOdds": 211
            }
          },
          "videos": [
            {
              "mediaId": "2556803653151",
              "timestamp": "2026-05-01T17:43:09"
            },
            {
              "mediaId": "2556809797126",
              "timestamp": "2026-05-01T17:56:13"
            }
          ]
        },
        {
          "id": "2026-05-01_24_2_2",
          "number": 2,
          "postPosition": 2,
          "distance": 2140,
          "horse": {
            "id": 787211,
            "name": "Garcon Francais",
            "age": 5,
            "sex": "gelding",
            "record": {
              "code": "M",
              "startMethod": "volte",
              "distance": "medium",
              "time": {
                "minutes": 1,
                "seconds": 16,
                "tenths": 9
              }
            },
            "trainer": {
              "id": 145636,
              "firstName": "Erik",
              "lastName": "Lindegren",
              "shortName": "Lin Er",
              "location": "L\u00f6vstabruk",
              "birth": 1973,
              "homeTrack": {
                "id": 16,
                "name": "G\u00e4vle"
              },
              "license": "A-tr\u00e4nare: tr\u00e4na, k\u00f6ra",
              "silks": "Mbl\u00e5, r\u00f6d/vit vinkel och \u00e4rmrev; mbl\u00e5",
              "statistics": {
                "years": {
                  "2025": {
                    "starts": 199,
                    "earnings": 224637600,
                    "placement": {
                      "3": 18,
                      "2": 20,
                      "1": 22
                    },
                    "winPercentage": 1105
                  },
                  "2026": {
                    "starts": 55,
                    "earnings": 30360000,
                    "placement": {
                      "3": 5,
                      "2": 5,
                      "1": 4
                    },
                    "winPercentage": 727
                  }
                }
              }
            },
            "shoes": {
              "reported": true,
              "front": {
                "hasShoe": true,
                "changed": false
              },
              "back": {
                "hasShoe": true,
                "changed": false
              }
            },
            "sulky": {
              "reported": true,
              "type": {
                "code": "VA",
                "text": "Vanlig",
                "engText": "Standard",
                "changed": false
              },
              "colour": {
                "code": "GU",
                "text": "Gul",
                "engText": "Yellow",
                "changed": false
              }
            },
            "money": 114300,
            "color": "brun",
            "homeTrack": {
              "id": 16,
              "name": "G\u00e4vle"
            },
            "owner": {
              "id": 813751,
              "name": "Mann Anna & Lindegren Erik"
            },
            "breeder": {
              "id": 454394,
              "name": "Lindegren Erik",
              "location": "L\u00f6vstabruk"
            },
            "statistics": {
              "years": {
                "2025": {
                  "starts": 7,
                  "earnings": 5500000,
                  "placement": {
                    "3": 0,
                    "2": 0,
                    "1": 1
                  },
                  "records": [
                    {
                      "code": "aK",
                      "startMethod": "auto",
                      "distance": "short",
                      "time": {
                        "minutes": 1,
                        "seconds": 15,
                        "tenths": 0
                      },
                      "place": 0
                    },
                    {
                      "code": "M",
                      "startMethod": "volte",
                      "distance": "medium",
                      "time": {
                        "minutes": 1,
                        "seconds": 17,
                        "tenths": 5
                      },
                      "place": 0
                    }
                  ]
                },
                "2026": {
                  "starts": 5,
                  "earnings": 1680000,
                  "placement": {
                    "3": 0,
                    "2": 0,
                    "1": 0
                  },
                  "records": [
                    {
                      "code": "aM",
                      "startMethod": "auto",
                      "distance": "medium",
                      "time": {
                        "minutes": 1,
                        "seconds": 15,
                        "tenths": 1
                      },
                      "place": 7
                    },
                    {
                      "code": "M",
                      "startMethod": "volte",
                      "distance": "medium",
                      "time": {
                        "minutes": 1,
                        "seconds": 16,
                        "tenths": 9
                      },
                      "place": 4
                    }
                  ]
                }
              },
              "life": {
                "starts": 17,
                "earnings": 11430000,
                "placement": {
                  "3": 1,
                  "2": 0,
                  "1": 2
                },
                "records": [
                  {
                    "code": "aK",
                    "startMethod": "auto",
                    "distance": "short",
                    "time": {
                      "minutes": 1,
                      "seconds": 15,
                      "tenths": 0
                    },
                    "place": 0,
                    "year": "2025"
                  },
                  {
                    "code": "aM",
                    "startMethod": "auto",
                    "distance": "medium",
                    "time": {
                      "minutes": 1,
                      "seconds": 15,
                      "tenths": 1
                    },
                    "place": 7,
                    "year": "2026"
                  },
                  {
                    "code": "aL",
                    "startMethod": "auto",
                    "distance": "long",
                    "time": {
                      "minutes": 1,
                      "seconds": 17,
                      "tenths": 5
                    },
                    "place": 0,
                    "year": "2025"
                  },
                  {
                    "code": "M",
                    "startMethod": "volte",
                    "distance": "medium",
                    "time": {
                      "minutes": 1,
                      "seconds": 16,
                      "tenths": 9
                    },
                    "place": 4,
                    "year": "2026"
                  }
                ],
                "winPercentage": 1176,
                "placePercentage": 1764,
                "earningsPerStart": 672352,
                "startPoints": 218
              },
              "lastFiveStarts": {
                "averageOdds": 5717
              }
            },
            "pedigree": {
              "father": {
                "id": 634079,
                "name": "Francais du Gull"
              },
              "mother": {
                "id": 729674,
                "name": "Edelsa"
              },
              "grandfather": {
                "id": 682635,
                "name": "Judge Joe",
                "nationality": "US"
              }
            }
          },
          "driver": {
            "id": 145636,
            "firstName": "Erik",
            "lastName": "Lindegren",
            "shortName": "Lin Er",
            "location": "L\u00f6vstabruk",
            "birth": 1973,
            "homeTrack": {
              "id": 16,
              "name": "G\u00e4vle"
            },
            "license": "A-tr\u00e4nare: tr\u00e4na, k\u00f6ra",
            "silks": "Mbl\u00e5, r\u00f6d/vit vinkel och \u00e4rmrev; mbl\u00e5",
            "statistics": {
              "years": {
                "2025": {
                  "starts": 136,
                  "earnings": 113838300,
                  "placement": {
                    "3": 16,
                    "2": 11,
                    "1": 9
                  },
                  "winPercentage": 661
                },
                "2026": {
                  "starts": 59,
                  "earnings": 31810000,
                  "placement": {
                    "3": 6,
                    "2": 5,
                    "1": 4
                  },
                  "winPercentage": 677
                }
              }
            }
          },
          "pools": {
            "vinnare": {
              "@type": ".VinnareStartPool",
              "odds": 2298
            },
            "plats": {
              "@type": ".PlatsStartPool",
              "minOdds": 332,
              "maxOdds": 332
            }
          },
          "videos": [
            {
              "mediaId": "2556790341474",
              "timestamp": "2026-05-01T17:10:43"
            },
            {
              "mediaId": "2556798021269",
              "timestamp": "2026-05-01T17:23:10"
            },
            {
              "mediaId": "2556804165137",
              "timestamp": "2026-05-01T17:33:17"
            },
            {
              "mediaId": "2556804677170",
              "timestamp": "2026-05-01T17:42:32"
            }
          ]
        },
        {
          "id": "2026-05-01_24_2_3",
          "number": 3,
          "postPosition": 3,
          "distance": 2140,
          "horse": {
            "id": 790973,
            "name": "Early Easter",
            "age": 4,
            "sex": "mare",
            "record": {
              "code": "K",
              "startMethod": "volte",
              "distance": "short",
              "time": {
                "minutes": 1,
                "seconds": 15,
                "tenths": 2
              }
            },
            "trainer": {
              "id": 52630,
              "firstName": "Bengt",
              "lastName": "Modig",
              "shortName": "Mod Be",
              "location": "R\u00e4ttvik",
              "birth": 1962,
              "homeTrack": {
                "id": 24,
                "name": "R\u00e4ttvik"
              },
              "license": "B-tr\u00e4nare: tr\u00e4na, k\u00f6ra f\u00f6r bolag",
              "statistics": {
                "years": {
                  "2025": {
                    "starts": 0,
                    "earnings": 0,
                    "placement": {
                      "3": 0,
                      "2": 0,
                      "1": 0
                    },
                    "winPercentage": 0
                  },
                  "2026": {
                    "starts": 3,
                    "earnings": 1540000,
                    "placement": {
                      "3": 0,
                      "2": 1,
                      "1": 0
                    },
                    "winPercentage": 0
                  }
                }
              }
            },
            "shoes": {
              "reported": true,
              "front": {
                "hasShoe": false,
                "changed": false
              },
              "back": {
                "hasShoe": false,
                "changed": true
              }
            },
            "sulky": {
              "reported": true,
              "type": {
                "code": "VA",
                "text": "Vanlig",
                "engText": "Standard",
                "changed": false
              },
              "colour": {
                "code": "GU",
                "text": "Gul",
                "engText": "Yellow",
                "changed": false
              }
            },
            "money": 77800,
            "color": "svartbrun",
            "homeTrack": {
              "id": 24,
              "name": "R\u00e4ttvik"
            },
            "owner": {
              "id": 698504,
              "name": "Modig Bengt, R\u00e4ttvik"
            },
            "breeder": {
              "id": 822062,
              "name": "Mudde's Bygg AB",
              "location": "R\u00e4ttvik"
            },
            "statistics": {
              "years": {
                "2025": {
                  "starts": 11,
                  "earnings": 6240000,
                  "placement": {
                    "3": 0,
                    "2": 0,
                    "1": 1
                  },
                  "records": [
                    {
                      "code": "aM",
                      "startMethod": "auto",
                      "distance": "medium",
                      "time": {
                        "minutes": 1,
                        "seconds": 14,
                        "tenths": 9
                      },
                      "place": 5
                    },
                    {
                      "code": "K",
                      "startMethod": "volte",
                      "distance": "short",
                      "time": {
                        "minutes": 1,
                        "seconds": 15,
                        "tenths": 2
                      },
                      "place": 1
                    }
                  ]
                },
                "2026": {
                  "starts": 3,
                  "earnings": 1540000,
                  "placement": {
                    "3": 0,
                    "2": 1,
                    "1": 0
                  },
                  "records": [
                    {
                      "code": "aK",
                      "startMethod": "auto",
                      "distance": "short",
                      "time": {
                        "minutes": 1,
                        "seconds": 17,
                        "tenths": 1
                      },
                      "place": 6
                    },
                    {
                      "code": "M",
                      "startMethod": "volte",
                      "distance": "medium",
                      "time": {
                        "minutes": 1,
                        "seconds": 16,
                        "tenths": 5
                      },
                      "place": 7
                    }
                  ]
                }
              },
              "life": {
                "starts": 14,
                "earnings": 7780000,
                "placement": {
                  "3": 0,
                  "2": 1,
                  "1": 1
                },
                "records": [
                  {
                    "code": "aK",
                    "startMethod": "auto",
                    "distance": "short",
                    "time": {
                      "minutes": 1,
                      "seconds": 17,
                      "tenths": 1
                    },
                    "place": 6,
                    "year": "2026"
                  },
                  {
                    "code": "aM",
                    "startMethod": "auto",
                    "distance": "medium",
                    "time": {
                      "minutes": 1,
                      "seconds": 14,
                      "tenths": 9
                    },
                    "place": 5,
                    "year": "2025"
                  },
                  {
                    "code": "K",
                    "startMethod": "volte",
                    "distance": "short",
                    "time": {
                      "minutes": 1,
                      "seconds": 15,
                      "tenths": 2
                    },
                    "place": 1,
                    "year": "2025"
                  },
                  {
                    "code": "M",
                    "startMethod": "volte",
                    "distance": "medium",
                    "time": {
                      "minutes": 1,
                      "seconds": 16,
                      "tenths": 5
                    },
                    "place": 7,
                    "year": "2026"
                  }
                ],
                "winPercentage": 714,
                "placePercentage": 1428,
                "earningsPerStart": 555714,
                "startPoints": 384
              },
              "lastFiveStarts": {
                "averageOdds": 3070
              }
            },
            "pedigree": {
              "father": {
                "id": 768774,
                "name": "Earl Simon",
                "nationality": "FR"
              },
              "mother": {
                "id": 708922,
                "name": "Chicago Tindra"
              },
              "grandfather": {
                "id": 185370,
                "name": "Igor Brick"
              }
            }
          },
          "driver": {
            "id": 674880,
            "firstName": "Nathalie",
            "lastName": "Blom",
            "shortName": "Blo Na",
            "location": "R\u00e4ttvik",
            "birth": 1991,
            "homeTrack": {
              "id": 24,
              "name": "R\u00e4ttvik"
            },
            "license": "A-tr\u00e4nare: tr\u00e4na, k\u00f6ra, rida",
            "silks": "Mbl\u00e5, cerise/silver axelsk\u00e4rp; mbl\u00e5",
            "statistics": {
              "years": {
                "2025": {
                  "starts": 266,
                  "earnings": 180535000,
                  "placement": {
                    "3": 24,
                    "2": 14,
                    "1": 9
                  },
                  "winPercentage": 338
                },
                "2026": {
                  "starts": 61,
                  "earnings": 47100000,
                  "placement": {
                    "3": 4,
                    "2": 5,
                    "1": 2
                  },
                  "winPercentage": 327
                }
              }
            }
          },
          "pools": {
            "vinnare": {
              "@type": ".VinnareStartPool",
              "odds": 1161
            },
            "plats": {
              "@type": ".PlatsStartPool",
              "minOdds": 216,
              "maxOdds": 216
            }
          },
          "videos": [
            {
              "mediaId": "2556804677172",
              "timestamp": "2026-05-01T17:42:47"
            }
          ]
        },
        {
          "id": "2026-05-01_24_2_4",
          "number": 4,
          "postPosition": 4,
          "distance": 2140,
          "horse": {
            "id": 771414,
            "name": "Tiffany M.M.",
            "age": 7,
            "sex": "mare",
            "record": {
              "code": "M",
              "startMethod": "volte",
              "distance": "medium",
              "time": {
                "minutes": 1,
                "seconds": 17,
                "tenths": 8
              }
            },
            "trainer": {
              "id": 700986,
              "firstName": "Frida",
              "lastName": "Asplund",
              "shortName": "Asp Fr",
              "location": "G\u00e4vle",
              "birth": 1994,
              "homeTrack": {
                "id": 16,
                "name": "G\u00e4vle"
              },
              "license": "B-tr\u00e4nare: tr\u00e4na, k\u00f6ra",
              "silks": "Svart, rosa axelp, h\u00e4ngslen och \u00e4rmb. ; vi",
              "statistics": {
                "years": {
                  "2025": {
                    "starts": 67,
                    "earnings": 28450000,
                    "placement": {
                      "3": 8,
                      "2": 3,
                      "1": 2
                    },
                    "winPercentage": 298
                  },
                  "2026": {
                    "starts": 25,
                    "earnings": 7050000,
                    "placement": {
                      "3": 0,
                      "2": 0,
                      "1": 1
                    },
                    "winPercentage": 400
                  }
                }
              }
            },
            "shoes": {
              "reported": true,
              "front": {
                "hasShoe": false,
                "changed": true
              },
              "back": {
                "hasShoe": true,
                "changed": false
              }
            },
            "sulky": {
              "reported": true,
              "type": {
                "code": "VA",
                "text": "Vanlig",
                "engText": "Standard",
                "changed": false
              },
              "colour": {
                "code": "GU",
                "text": "Gul",
                "engText": "Yellow",
                "changed": false
              }
            },
            "money": 62800,
            "color": "brun",
            "homeTrack": {
              "id": 16,
              "name": "G\u00e4vle"
            },
            "owner": {
              "id": 735839,
              "name": "Asplund Frida, G\u00e4vle"
            },
            "breeder": {
              "id": 508416,
              "name": "Johansson Magdalena & Waage Morten"
            },
            "statistics": {
              "years": {
                "2025": {
                  "starts": 15,
                  "earnings": 4850000,
                  "placement": {
                    "3": 3,
                    "2": 0,
                    "1": 0
                  },
                  "records": [
                    {
                      "code": "aK",
                      "startMethod": "auto",
                      "distance": "short",
                      "time": {
                        "minutes": 1,
                        "seconds": 15,
                        "tenths": 6
                      },
                      "place": 3
                    },
                    {
                      "code": "M",
                      "startMethod": "volte",
                      "distance": "medium",
                      "time": {
                        "minutes": 1,
                        "seconds": 17,
                        "tenths": 8
                      },
                      "place": 7
                    }
                  ]
                },
                "2026": {
                  "starts": 7,
                  "earnings": 1430000,
                  "placement": {
                    "3": 0,
                    "2": 0,
                    "1": 0
                  },
                  "records": [
                    {
                      "code": "aM",
                      "startMethod": "auto",
                      "distance": "medium",
                      "time": {
                        "minutes": 1,
                        "seconds": 16,
                        "tenths": 1
                      },
                      "place": 0
                    },
                    {
                      "code": "M",
                      "startMethod": "volte",
                      "distance": "medium",
                      "time": {
                        "minutes": 1,
                        "seconds": 18,
                        "tenths": 1
                      },
                      "place": 0
                    }
                  ]
                }
              },
              "life": {
                "starts": 22,
                "earnings": 6280000,
                "placement": {
                  "3": 3,
                  "2": 0,
                  "1": 0
                },
                "records": [
                  {
                    "code": "aK",
                    "startMethod": "auto",
                    "distance": "short",
                    "time": {
                      "minutes": 1,
                      "seconds": 15,
                      "tenths": 6
                    },
                    "place": 3,
                    "year": "2025"
                  },
                  {
                    "code": "aM",
                    "startMethod": "auto",
                    "distance": "medium",
                    "time": {
                      "minutes": 1,
                      "seconds": 16,
                      "tenths": 1
                    },
                    "place": 0,
                    "year": "2026"
                  },
                  {
                    "code": "M",
                    "startMethod": "volte",
                    "distance": "medium",
                    "time": {
                      "minutes": 1,
                      "seconds": 17,
                      "tenths": 8
                    },
                    "place": 7,
                    "year": "2025"
                  }
                ],
                "winPercentage": 0,
                "placePercentage": 1363,
                "earningsPerStart": 285454,
                "startPoints": 138
              },
              "lastFiveStarts": {
                "averageOdds": 10998
              }
            },
            "pedigree": {
              "father": {
                "id": 636691,
                "name": "Raja Mirchi"
              },
              "mother": {
                "id": 573723,
                "name": "Phoebe M.M."
              },
              "grandfather": {
                "id": 161030,
                "name": "Super Arnie",
                "nationality": "US"
              }
            }
          },
          "driver": {
            "id": 700986,
            "firstName": "Frida",
            "lastName": "Asplund",
            "shortName": "Asp Fr",
            "location": "G\u00e4vle",
            "birth": 1994,
            "homeTrack": {
              "id": 16,
              "name": "G\u00e4vle"
            },
            "license": "B-tr\u00e4nare: tr\u00e4na, k\u00f6ra",
            "silks": "Svart, rosa axelp, h\u00e4ngslen och \u00e4rmb. ; vi",
            "statistics": {
              "years": {
                "2025": {
                  "starts": 89,
                  "earnings": 34810000,
                  "placement": {
                    "3": 10,
                    "2": 4,
                    "1": 2
                  },
                  "winPercentage": 224
                },
                "2026": {
                  "starts": 43,
                  "earnings": 13640000,
                  "placement": {
                    "3": 2,
                    "2": 0,
                    "1": 1
                  },
                  "winPercentage": 232
                }
              }
            }
          },
          "pools": {
            "vinnare": {
              "@type": ".VinnareStartPool",
              "odds": 6386
            },
            "plats": {
              "@type": ".PlatsStartPool",
              "minOdds": 783,
              "maxOdds": 783
            }
          },
          "videos": [
            {
              "mediaId": "2556800069411",
              "timestamp": "2026-05-01T17:30:41"
            },
            {
              "mediaId": "2556803653173",
              "timestamp": "2026-05-01T17:44:01"
            },
            {
              "mediaId": "2556808261270",
              "timestamp": "2026-05-01T17:54:06"
            }
          ]
        },
        {
          "id": "2026-05-01_24_2_5",
          "number": 5,
          "postPosition": 5,
          "distance": 2140,
          "horse": {
            "id": 782776,
            "name": "Lepshij",
            "nationality": "RU",
            "age": 7,
            "sex": "gelding",
            "record": {
              "code": "L",
              "startMethod": "volte",
              "distance": "long",
              "time": {
                "minutes": 1,
                "seconds": 17,
                "tenths": 3
              }
            },
            "trainer": {
              "id": 505072,
              "firstName": "Jevgeni",
              "lastName": "Ivanov",
              "shortName": "Iva Je",
              "location": "Almunge",
              "birth": 1975,
              "homeTrack": {
                "id": 5,
                "name": "Solvalla"
              },
              "license": "A-tr\u00e4nare: (Sv/utland): tr\u00e4na, k\u00f6ra",
              "silks": "Svart, gul/vit/m\u00f6rkbl\u00e5 vinklar; vit",
              "statistics": {
                "years": {
                  "2025": {
                    "starts": 232,
                    "earnings": 178688500,
                    "placement": {
                      "3": 17,
                      "2": 21,
                      "1": 34
                    },
                    "winPercentage": 1465
                  },
                  "2026": {
                    "starts": 106,
                    "earnings": 85613400,
                    "placement": {
                      "3": 10,
                      "2": 7,
                      "1": 7
                    },
                    "winPercentage": 660
                  }
                }
              }
            },
            "shoes": {
              "reported": true,
              "front": {
                "hasShoe": false,
                "changed": false
              },
              "back": {
                "hasShoe": false,
                "changed": false
              }
            },
            "sulky": {
              "reported": true,
              "type": {
                "code": "VA",
                "text": "Vanlig",
                "engText": "Standard",
                "changed": false
              },
              "colour": {
                "code": "GU",
                "text": "Gul",
                "engText": "Yellow",
                "changed": false
              }
            },
            "money": 134721,
            "color": "brun",
            "homeTrack": {
              "id": 5,
              "name": "Solvalla"
            },
            "owner": {
              "id": 708340,
              "name": "Fironova Jelena, Estland"
            },
            "breeder": {
              "id": 778839,
              "name": "Gabuev Murat",
              "location": "Ryssland"
            },
            "statistics": {
              "years": {
                "2025": {
                  "starts": 6,
                  "earnings": 4414200,
                  "placement": {
                    "3": 2,
                    "2": 0,
                    "1": 1
                  },
                  "records": [
                    {
                      "code": "aM",
                      "startMethod": "auto",
                      "distance": "medium",
                      "time": {
                        "minutes": 1,
                        "seconds": 15,
                        "tenths": 3
                      },
                      "place": 1
                    },
                    {
                      "code": "L",
                      "startMethod": "volte",
                      "distance": "long",
                      "time": {
                        "minutes": 1,
                        "seconds": 17,
                        "tenths": 3
                      },
                      "place": 4
                    }
                  ]
                },
                "2026": {
                  "starts": 5,
                  "earnings": 1986800,
                  "placement": {
                    "3": 1,
                    "2": 0,
                    "1": 0
                  },
                  "records": [
                    {
                      "code": "aL",
                      "startMethod": "auto",
                      "distance": "long",
                      "time": {
                        "minutes": 1,
                        "seconds": 20,
                        "tenths": 3
                      },
                      "place": 3
                    },
                    {
                      "code": "L",
                      "startMethod": "volte",
                      "distance": "long",
                      "time": {
                        "minutes": 1,
                        "seconds": 18,
                        "tenths": 0
                      },
                      "place": 0
                    }
                  ]
                }
              },
              "life": {
                "starts": 40,
                "earnings": 13472100,
                "placement": {
                  "3": 5,
                  "2": 5,
                  "1": 6
                },
                "records": [
                  {
                    "code": "aL",
                    "startMethod": "auto",
                    "distance": "long",
                    "time": {
                      "minutes": 1,
                      "seconds": 15,
                      "tenths": 3
                    },
                    "place": 3,
                    "year": "2025"
                  },
                  {
                    "code": "L",
                    "startMethod": "volte",
                    "distance": "long",
                    "time": {
                      "minutes": 1,
                      "seconds": 17,
                      "tenths": 3
                    },
                    "place": 4,
                    "year": "2025"
                  }
                ],
                "winPercentage": 1500,
                "placePercentage": 4000,
                "earningsPerStart": 336802,
                "startPoints": 298
              },
              "lastFiveStarts": {
                "averageOdds": 5195
              }
            },
            "pedigree": {
              "father": {
                "id": 724593,
                "name": "Perseus Face"
              },
              "mother": {
                "id": 658543,
                "name": "Lullaby Face"
              },
              "grandfather": {
                "id": 202234,
                "name": "Viking Kronos",
                "nationality": "IT"
              }
            },
            "foreignOwned": true
          },
          "driver": {
            "id": 505072,
            "firstName": "Jevgeni",
            "lastName": "Ivanov",
            "shortName": "Iva Je",
            "location": "Almunge",
            "birth": 1975,
            "homeTrack": {
              "id": 5,
              "name": "Solvalla"
            },
            "license": "A-tr\u00e4nare: (Sv/utland): tr\u00e4na, k\u00f6ra",
            "silks": "Svart, gul/vit/m\u00f6rkbl\u00e5 vinklar; vit",
            "statistics": {
              "years": {
                "2025": {
                  "starts": 154,
                  "earnings": 102282300,
                  "placement": {
                    "3": 9,
                    "2": 12,
                    "1": 26
                  },
                  "winPercentage": 1688
                },
                "2026": {
                  "starts": 53,
                  "earnings": 41831100,
                  "placement": {
                    "3": 2,
                    "2": 3,
                    "1": 4
                  },
                  "winPercentage": 754
                }
              }
            }
          },
          "pools": {
            "vinnare": {
              "@type": ".VinnareStartPool",
              "odds": 833
            },
            "plats": {
              "@type": ".PlatsStartPool",
              "minOdds": 261,
              "maxOdds": 261
            }
          },
          "videos": [
            {
              "mediaId": "2556803141115",
              "timestamp": "2026-05-01T17:29:42"
            },
            {
              "mediaId": "2556804677030",
              "timestamp": "2026-05-01T17:40:20"
            }
          ]
        },
        {
          "id": "2026-05-01_24_2_6",
          "number": 6,
          "postPosition": 6,
          "distance": 2140,
          "horse": {
            "id": 766459,
            "name": "Miss Lindra",
            "age": 8,
            "sex": "mare",
            "record": {
              "code": "K",
              "startMethod": "volte",
              "distance": "short",
              "time": {
                "minutes": 1,
                "seconds": 16,
                "tenths": 1
              }
            },
            "trainer": {
              "id": 1074,
              "firstName": "Johnny",
              "lastName": "Hermansson",
              "shortName": "Her Jo",
              "location": "Vikarbyn",
              "birth": 1943,
              "homeTrack": {
                "id": 24,
                "name": "R\u00e4ttvik"
              },
              "license": "B-tr\u00e4nare: tr\u00e4na, k\u00f6ra f\u00f6r bolag",
              "silks": "Gul, svart axelparti och \u00e4rms\u00f6mmar; vit",
              "statistics": {
                "years": {
                  "2025": {
                    "starts": 11,
                    "earnings": 2790000,
                    "placement": {
                      "3": 1,
                      "2": 0,
                      "1": 0
                    },
                    "winPercentage": 0
                  },
                  "2026": {
                    "starts": 1,
                    "earnings": 230000,
                    "placement": {
                      "3": 0,
                      "2": 0,
                      "1": 0
                    },
                    "winPercentage": 0
                  }
                }
              }
            },
            "shoes": {
              "reported": true,
              "front": {
                "hasShoe": true,
                "changed": false
              },
              "back": {
                "hasShoe": false,
                "changed": true
              }
            },
            "sulky": {
              "reported": true,
              "type": {
                "code": "VA",
                "text": "Vanlig",
                "engText": "Standard",
                "changed": false
              },
              "colour": {
                "code": "GU",
                "text": "Gul",
                "engText": "Yellow",
                "changed": false
              }
            },
            "money": 127400,
            "color": "fux",
            "homeTrack": {
              "id": 24,
              "name": "R\u00e4ttvik"
            },
            "owner": {
              "id": 563743,
              "name": "Hermansson Johnny & Jenny"
            },
            "breeder": {
              "id": 200282,
              "name": "Hermansson Johnny",
              "location": "Vikarbyn"
            },
            "statistics": {
              "years": {
                "2025": {
                  "starts": 11,
                  "earnings": 2790000,
                  "placement": {
                    "3": 1,
                    "2": 0,
                    "1": 0
                  },
                  "records": [
                    {
                      "code": "aM",
                      "startMethod": "auto",
                      "distance": "medium",
                      "time": {
                        "minutes": 1,
                        "seconds": 17,
                        "tenths": 6
                      },
                      "place": 5
                    },
                    {
                      "code": "K",
                      "startMethod": "volte",
                      "distance": "short",
                      "time": {
                        "minutes": 1,
                        "seconds": 16,
                        "tenths": 1
                      },
                      "place": 0
                    }
                  ]
                },
                "2026": {
                  "starts": 1,
                  "earnings": 230000,
                  "placement": {
                    "3": 0,
                    "2": 0,
                    "1": 0
                  },
                  "records": [
                    {
                      "code": "M",
                      "startMethod": "volte",
                      "distance": "medium",
                      "time": {
                        "minutes": 1,
                        "seconds": 17,
                        "tenths": 9
                      },
                      "place": 8
                    }
                  ]
                }
              },
              "life": {
                "starts": 53,
                "earnings": 12740000,
                "placement": {
                  "3": 5,
                  "2": 1,
                  "1": 0
                },
                "records": [
                  {
                    "code": "aK",
                    "startMethod": "auto",
                    "distance": "short",
                    "time": {
                      "minutes": 1,
                      "seconds": 14,
                      "tenths": 9
                    },
                    "place": 4,
                    "year": "2024"
                  },
                  {
                    "code": "aM",
                    "startMethod": "auto",
                    "distance": "medium",
                    "time": {
                      "minutes": 1,
                      "seconds": 16,
                      "tenths": 4
                    },
                    "place": 0,
                    "year": "2024"
                  },
                  {
                    "code": "aL",
                    "startMethod": "auto",
                    "distance": "long",
                    "time": {
                      "minutes": 1,
                      "seconds": 21,
                      "tenths": 6
                    },
                    "place": 7,
                    "year": "2024"
                  },
                  {
                    "code": "K",
                    "startMethod": "volte",
                    "distance": "short",
                    "time": {
                      "minutes": 1,
                      "seconds": 16,
                      "tenths": 1
                    },
                    "place": 0,
                    "year": "2025"
                  },
                  {
                    "code": "M",
                    "startMethod": "volte",
                    "distance": "medium",
                    "time": {
                      "minutes": 1,
                      "seconds": 16,
                      "tenths": 4
                    },
                    "place": 8,
                    "year": "2025"
                  }
                ],
                "winPercentage": 0,
                "placePercentage": 1132,
                "earningsPerStart": 240377,
                "startPoints": 241
              },
              "lastFiveStarts": {
                "averageOdds": 8140
              }
            },
            "pedigree": {
              "father": {
                "id": 580790,
                "name": "Kr\u00e5ngel"
              },
              "mother": {
                "id": 199848,
                "name": "Madam Mizar"
              },
              "grandfather": {
                "id": 4491,
                "name": "Anders Crown",
                "nationality": "US"
              }
            }
          },
          "driver": {
            "id": 86309,
            "firstName": "Katrin K",
            "lastName": "Frick",
            "shortName": "Fri KK",
            "location": "R\u00e4ttvik",
            "birth": 1981,
            "homeTrack": {
              "id": 24,
              "name": "R\u00e4ttvik"
            },
            "license": "A-tr\u00e4nare: tr\u00e4na, k\u00f6ra",
            "silks": "M\u00f6rkbl\u00e5, lila lodr\u00e4tt f\u00e4lt; m\u00f6rkbl\u00e5",
            "statistics": {
              "years": {
                "2025": {
                  "starts": 116,
                  "earnings": 77610000,
                  "placement": {
                    "3": 7,
                    "2": 12,
                    "1": 4
                  },
                  "winPercentage": 344
                },
                "2026": {
                  "starts": 48,
                  "earnings": 36525000,
                  "placement": {
                    "3": 4,
                    "2": 5,
                    "1": 3
                  },
                  "winPercentage": 625
                }
              }
            }
          },
          "pools": {
            "vinnare": {
              "@type": ".VinnareStartPool",
              "odds": 3255
            },
            "plats": {
              "@type": ".PlatsStartPool",
              "minOdds": 402,
              "maxOdds": 402
            }
          }
        },
        {
          "id": "2026-05-01_24_2_7",
          "number": 7,
          "scratched": true,
          "postPosition": 7,
          "distance": 2140,
          "horse": {
            "id": 763813,
            "name": "Dream From Above",
            "age": 8,
            "sex": "mare",
            "record": {
              "code": "K",
              "startMethod": "volte",
              "distance": "short",
              "time": {
                "minutes": 1,
                "seconds": 15,
                "tenths": 8
              }
            },
            "trainer": {
              "id": 17355,
              "firstName": "Claes",
              "lastName": "Eskilsson",
              "shortName": "Esk Cl",
              "location": "Gustafs",
              "birth": 1966,
              "homeTrack": {
                "id": 23,
                "name": "Romme"
              },
              "license": "A-tr\u00e4nare: tr\u00e4na, k\u00f6ra",
              "silks": "Bl\u00e5, vit axp. och stolpar, bl\u00e5/r\u00f6d \u00e4rm; bl",
              "statistics": {
                "years": {
                  "2025": {
                    "starts": 82,
                    "earnings": 37180000,
                    "placement": {
                      "3": 5,
                      "2": 5,
                      "1": 3
                    },
                    "winPercentage": 365
                  },
                  "2026": {
                    "starts": 47,
                    "earnings": 17960000,
                    "placement": {
                      "3": 5,
                      "2": 0,
                      "1": 1
                    },
                    "winPercentage": 212
                  }
                }
              }
            },
            "shoes": {
              "reported": true,
              "front": {
                "hasShoe": false,
                "changed": true
              },
              "back": {
                "hasShoe": true,
                "changed": false
              }
            },
            "sulky": {
              "reported": true,
              "type": {
                "code": "VA",
                "text": "Vanlig",
                "engText": "Standard",
                "changed": false
              },
              "colour": {
                "code": "GU",
                "text": "Gul",
                "engText": "Yellow",
                "changed": false
              }
            },
            "money": 108200,
            "color": "m\u00f6rkbrun",
            "homeTrack": {
              "id": 23,
              "name": "Romme"
            },
            "owner": {
              "id": 573084,
              "name": "Blomkvist Lars-Ove, Gagnef"
            },
            "breeder": {
              "id": 715769,
              "name": "Eriksson Maria & Blomkvist Lars-Ove"
            },
            "statistics": {
              "years": {
                "2025": {
                  "starts": 8,
                  "earnings": 3300000,
                  "placement": {
                    "3": 0,
                    "2": 0,
                    "1": 1
                  },
                  "records": [
                    {
                      "code": "aK",
                      "startMethod": "auto",
                      "distance": "short",
                      "time": {
                        "minutes": 1,
                        "seconds": 15,
                        "tenths": 2
                      },
                      "place": 1
                    },
                    {
                      "code": "K",
                      "startMethod": "volte",
                      "distance": "short",
                      "time": {
                        "minutes": 1,
                        "seconds": 15,
                        "tenths": 8
                      },
                      "place": 6
                    }
                  ]
                },
                "2026": {
                  "starts": 6,
                  "earnings": 2740000,
                  "placement": {
                    "3": 1,
                    "2": 0,
                    "1": 0
                  },
                  "records": [
                    {
                      "code": "aM",
                      "startMethod": "auto",
                      "distance": "medium",
                      "time": {
                        "minutes": 1,
                        "seconds": 16,
                        "tenths": 4
                      },
                      "place": 0
                    },
                    {
                      "code": "M",
                      "startMethod": "volte",
                      "distance": "medium",
                      "time": {
                        "minutes": 1,
                        "seconds": 16,
                        "tenths": 8
                      },
                      "place": 4
                    }
                  ]
                }
              },
              "life": {
                "starts": 29,
                "earnings": 10820000,
                "placement": {
                  "3": 1,
                  "2": 0,
                  "1": 2
                },
                "records": [
                  {
                    "code": "aK",
                    "startMethod": "auto",
                    "distance": "short",
                    "time": {
                      "minutes": 1,
                      "seconds": 15,
                      "tenths": 2
                    },
                    "place": 1,
                    "year": "2025"
                  },
                  {
                    "code": "aM",
                    "startMethod": "auto",
                    "distance": "medium",
                    "time": {
                      "minutes": 1,
                      "seconds": 15,
                      "tenths": 8
                    },
                    "place": 1,
                    "year": "2024"
                  },
                  {
                    "code": "K",
                    "startMethod": "volte",
                    "distance": "short",
                    "time": {
                      "minutes": 1,
                      "seconds": 15,
                      "tenths": 8
                    },
                    "place": 6,
                    "year": "2025"
                  },
                  {
                    "code": "M",
                    "startMethod": "volte",
                    "distance": "medium",
                    "time": {
                      "minutes": 1,
                      "seconds": 16,
                      "tenths": 6
                    },
                    "place": 7,
                    "year": "2025"
                  }
                ],
                "winPercentage": 689,
                "placePercentage": 1034,
                "earningsPerStart": 373103,
                "startPoints": 399
              },
              "lastFiveStarts": {
                "averageOdds": 5328
              }
            },
            "pedigree": {
              "father": {
                "id": 426861,
                "name": "From Above"
              },
              "mother": {
                "id": 702019,
                "name": "Maya's Dream"
              },
              "grandfather": {
                "id": 628251,
                "name": "Offshore Dream",
                "nationality": "FR"
              }
            }
          },
          "driver": {
            "id": 17355,
            "firstName": "Claes",
            "lastName": "Eskilsson",
            "shortName": "Esk Cl",
            "location": "Gustafs",
            "birth": 1966,
            "homeTrack": {
              "id": 23,
              "name": "Romme"
            },
            "license": "A-tr\u00e4nare: tr\u00e4na, k\u00f6ra",
            "silks": "Bl\u00e5, vit axp. och stolpar, bl\u00e5/r\u00f6d \u00e4rm; bl",
            "statistics": {
              "years": {
                "2025": {
                  "starts": 113,
                  "earnings": 67030000,
                  "placement": {
                    "3": 4,
                    "2": 4,
                    "1": 6
                  },
                  "winPercentage": 530
                },
                "2026": {
                  "starts": 46,
                  "earnings": 23710000,
                  "placement": {
                    "3": 3,
                    "2": 1,
                    "1": 2
                  },
                  "winPercentage": 434
                }
              }
            }
          },
          "pools": {
            "vinnare": {
              "@type": ".VinnareStartPool",
              "odds": 0
            },
            "plats": {
              "@type": ".PlatsStartPool",
              "minOdds": 0,
              "maxOdds": 0
            }
          }
        },
        {
          "id": "2026-05-01_24_2_8",
          "number": 8,
          "postPosition": 8,
          "distance": 2140,
          "horse": {
            "id": 783771,
            "name": "Dream Loverboy",
            "age": 5,
            "sex": "gelding",
            "record": {
              "code": "M",
              "startMethod": "volte",
              "distance": "medium",
              "time": {
                "minutes": 1,
                "seconds": 16,
                "tenths": 5
              }
            },
            "trainer": {
              "id": 593763,
              "firstName": "Mattias",
              "lastName": "Djuse",
              "shortName": "Dju Ma",
              "location": "Ekolsund",
              "birth": 1989,
              "homeTrack": {
                "id": 5,
                "name": "Solvalla"
              },
              "license": "A-tr\u00e4nare: tr\u00e4na, k\u00f6ra",
              "silks": "Svart, silver sidor, br\u00f6stb. och \u00e4rmb.; sv",
              "statistics": {
                "years": {
                  "2025": {
                    "starts": 754,
                    "earnings": 2124418600,
                    "placement": {
                      "3": 93,
                      "2": 91,
                      "1": 128
                    },
                    "winPercentage": 1697
                  },
                  "2026": {
                    "starts": 253,
                    "earnings": 697109800,
                    "placement": {
                      "3": 35,
                      "2": 31,
                      "1": 55
                    },
                    "winPercentage": 2173
                  }
                }
              }
            },
            "shoes": {
              "reported": true,
              "front": {
                "hasShoe": false,
                "changed": false
              },
              "back": {
                "hasShoe": true,
                "changed": false
              }
            },
            "sulky": {
              "reported": true,
              "type": {
                "code": "VA",
                "text": "Vanlig",
                "engText": "Standard",
                "changed": false
              },
              "colour": {
                "code": "GU",
                "text": "Gul",
                "engText": "Yellow",
                "changed": false
              }
            },
            "money": 157000,
            "color": "brun",
            "homeTrack": {
              "id": 5,
              "name": "Solvalla"
            },
            "owner": {
              "id": 678891,
              "name": "Dicks Hush\u00e5llsservice AB, M\u00e5rd A-L & D"
            },
            "breeder": {
              "id": 215947,
              "name": "Global Farm AB",
              "location": "Nacka Strand"
            },
            "statistics": {
              "years": {
                "2025": {
                  "starts": 3,
                  "earnings": 1800000,
                  "placement": {
                    "3": 0,
                    "2": 1,
                    "1": 0
                  },
                  "records": [
                    {
                      "code": "aM",
                      "startMethod": "auto",
                      "distance": "medium",
                      "time": {
                        "minutes": 1,
                        "seconds": 16,
                        "tenths": 0
                      },
                      "place": 2
                    }
                  ]
                },
                "2026": {
                  "starts": 8,
                  "earnings": 11750000,
                  "placement": {
                    "3": 0,
                    "2": 0,
                    "1": 2
                  },
                  "records": [
                    {
                      "code": "aM",
                      "startMethod": "auto",
                      "distance": "medium",
                      "time": {
                        "minutes": 1,
                        "seconds": 13,
                        "tenths": 3
                      },
                      "place": 0
                    }
                  ]
                }
              },
              "life": {
                "starts": 13,
                "earnings": 15700000,
                "placement": {
                  "3": 0,
                  "2": 2,
                  "1": 2
                },
                "records": [
                  {
                    "code": "aM",
                    "startMethod": "auto",
                    "distance": "medium",
                    "time": {
                      "minutes": 1,
                      "seconds": 13,
                      "tenths": 3
                    },
                    "place": 0,
                    "year": "2026"
                  },
                  {
                    "code": "aL",
                    "startMethod": "auto",
                    "distance": "long",
                    "time": {
                      "minutes": 1,
                      "seconds": 15,
                      "tenths": 2
                    },
                    "place": 6,
                    "year": "2026"
                  },
                  {
                    "code": "M",
                    "startMethod": "volte",
                    "distance": "medium",
                    "time": {
                      "minutes": 1,
                      "seconds": 16,
                      "tenths": 5
                    },
                    "place": 2,
                    "year": "2024"
                  }
                ],
                "winPercentage": 1538,
                "placePercentage": 3076,
                "earningsPerStart": 1207692,
                "startPoints": 210
              },
              "lastFiveStarts": {
                "averageOdds": 2547
              }
            },
            "pedigree": {
              "father": {
                "id": 718800,
                "name": "Uniclove",
                "nationality": "FR"
              },
              "mother": {
                "id": 637507,
                "name": "Song Glider"
              },
              "grandfather": {
                "id": 579264,
                "name": "Windsong's Legacy",
                "nationality": "US"
              }
            }
          },
          "driver": {
            "id": 593763,
            "firstName": "Mattias",
            "lastName": "Djuse",
            "shortName": "Dju Ma",
            "location": "Ekolsund",
            "birth": 1989,
            "homeTrack": {
              "id": 5,
              "name": "Solvalla"
            },
            "license": "A-tr\u00e4nare: tr\u00e4na, k\u00f6ra",
            "silks": "Svart, silver sidor, br\u00f6stb. och \u00e4rmb.; sv",
            "statistics": {
              "years": {
                "2025": {
                  "starts": 71,
                  "earnings": 91710000,
                  "placement": {
                    "3": 14,
                    "2": 5,
                    "1": 10
                  },
                  "winPercentage": 1408
                },
                "2026": {
                  "starts": 26,
                  "earnings": 31550000,
                  "placement": {
                    "3": 5,
                    "2": 2,
                    "1": 2
                  },
                  "winPercentage": 769
                }
              }
            }
          },
          "pools": {
            "vinnare": {
              "@type": ".VinnareStartPool",
              "odds": 181
            },
            "plats": {
              "@type": ".PlatsStartPool",
              "minOdds": 119,
              "maxOdds": 119
            }
          },
          "videos": [
            {
              "mediaId": "2556798021391",
              "timestamp": "2026-05-01T17:29:42"
            },
            {
              "mediaId": "2556804677157",
              "timestamp": "2026-05-01T17:42:20"
            }
          ]
        },
        {
          "id": "2026-05-01_24_2_9",
          "number": 9,
          "postPosition": 1,
          "distance": 2160,
          "horse": {
            "id": 794904,
            "name": "Against All Odds",
            "age": 4,
            "sex": "gelding",
            "record": {
              "code": "M",
              "startMethod": "volte",
              "distance": "medium",
              "time": {
                "minutes": 1,
                "seconds": 15,
                "tenths": 6
              }
            },
            "trainer": {
              "id": 503386,
              "firstName": "Katja",
              "lastName": "Melkko",
              "shortName": "Mel Ka",
              "location": "Borl\u00e4nge",
              "birth": 1977,
              "homeTrack": {
                "id": 23,
                "name": "Romme"
              },
              "license": "A-tr\u00e4nare: (Sv/utland): tr\u00e4na, k\u00f6ra",
              "silks": "R\u00f6d, svart, vit; svart",
              "statistics": {
                "years": {
                  "2025": {
                    "starts": 267,
                    "earnings": 631316100,
                    "placement": {
                      "3": 35,
                      "2": 30,
                      "1": 53
                    },
                    "winPercentage": 1985
                  },
                  "2026": {
                    "starts": 67,
                    "earnings": 184520000,
                    "placement": {
                      "3": 12,
                      "2": 9,
                      "1": 15
                    },
                    "winPercentage": 2238
                  }
                }
              }
            },
            "shoes": {
              "reported": true,
              "front": {
                "hasShoe": true,
                "changed": true
              },
              "back": {
                "hasShoe": true,
                "changed": false
              }
            },
            "sulky": {
              "reported": true,
              "type": {
                "code": "VA",
                "text": "Vanlig",
                "engText": "Standard",
                "changed": false
              },
              "colour": {
                "code": "GU",
                "text": "Gul",
                "engText": "Yellow",
                "changed": false
              }
            },
            "money": 141800,
            "color": "brun",
            "homeTrack": {
              "id": 23,
              "name": "Romme"
            },
            "owner": {
              "id": 821981,
              "name": "Kj Sport Horses AB(Melkko Katja), m fl"
            },
            "breeder": {
              "id": 821981,
              "name": "Kj Sport Horses AB(Melkko Katja)"
            },
            "statistics": {
              "years": {
                "2025": {
                  "starts": 6,
                  "earnings": 11750000,
                  "placement": {
                    "3": 1,
                    "2": 1,
                    "1": 2
                  },
                  "records": [
                    {
                      "code": "aM",
                      "startMethod": "auto",
                      "distance": "medium",
                      "time": {
                        "minutes": 1,
                        "seconds": 15,
                        "tenths": 2
                      },
                      "place": 4
                    },
                    {
                      "code": "M",
                      "startMethod": "volte",
                      "distance": "medium",
                      "time": {
                        "minutes": 1,
                        "seconds": 15,
                        "tenths": 7
                      },
                      "place": 1
                    }
                  ]
                },
                "2026": {
                  "starts": 4,
                  "earnings": 2430000,
                  "placement": {
                    "3": 0,
                    "2": 1,
                    "1": 0
                  },
                  "records": [
                    {
                      "code": "aM",
                      "startMethod": "auto",
                      "distance": "medium",
                      "time": {
                        "minutes": 1,
                        "seconds": 14,
                        "tenths": 6
                      },
                      "place": 5
                    },
                    {
                      "code": "M",
                      "startMethod": "volte",
                      "distance": "medium",
                      "time": {
                        "minutes": 1,
                        "seconds": 15,
                        "tenths": 6
                      },
                      "place": 2
                    }
                  ]
                }
              },
              "life": {
                "starts": 10,
                "earnings": 14180000,
                "placement": {
                  "3": 1,
                  "2": 2,
                  "1": 2
                },
                "records": [
                  {
                    "code": "aK",
                    "startMethod": "auto",
                    "distance": "short",
                    "time": {
                      "minutes": 1,
                      "seconds": 15,
                      "tenths": 1
                    },
                    "place": 8,
                    "year": "2026"
                  },
                  {
                    "code": "aM",
                    "startMethod": "auto",
                    "distance": "medium",
                    "time": {
                      "minutes": 1,
                      "seconds": 14,
                      "tenths": 6
                    },
                    "place": 5,
                    "year": "2026"
                  },
                  {
                    "code": "M",
                    "startMethod": "volte",
                    "distance": "medium",
                    "time": {
                      "minutes": 1,
                      "seconds": 15,
                      "tenths": 6
                    },
                    "place": 2,
                    "year": "2026"
                  }
                ],
                "winPercentage": 2000,
                "placePercentage": 5000,
                "earningsPerStart": 1418000,
                "startPoints": 618
              },
              "lastFiveStarts": {
                "averageOdds": 1347
              }
            },
            "pedigree": {
              "father": {
                "id": 553396,
                "name": "S.J.'s Caviar",
                "nationality": "US"
              },
              "mother": {
                "id": 760808,
                "name": "Honey Journey"
              },
              "grandfather": {
                "id": 484805,
                "name": "Scarlet Knight",
                "nationality": "US"
              }
            }
          },
          "driver": {
            "id": 637822,
            "firstName": "Janne",
            "lastName": "Soronen",
            "shortName": "Sor Ja",
            "location": "Borl\u00e4nge",
            "birth": 1979,
            "homeTrack": {
              "id": 23,
              "name": "Romme"
            },
            "license": "K\u00f6rlicens kategori 1: k\u00f6ra",
            "silks": "R\u00f6d, svarta sidor; r\u00f6d",
            "statistics": {
              "years": {
                "2025": {
                  "starts": 8,
                  "earnings": 4800000,
                  "placement": {
                    "3": 0,
                    "2": 2,
                    "1": 2
                  },
                  "winPercentage": 2500
                },
                "2026": {
                  "starts": 9,
                  "earnings": 10100000,
                  "placement": {
                    "3": 2,
                    "2": 5,
                    "1": 0
                  },
                  "winPercentage": 0
                }
              }
            }
          },
          "pools": {
            "vinnare": {
              "@type": ".VinnareStartPool",
              "odds": 408
            },
            "plats": {
              "@type": ".PlatsStartPool",
              "minOdds": 140,
              "maxOdds": 140
            }
          }
        }
      ],
      "mergedPools": [
        {
          "name": "A",
          "betTypes": [
            "vinnare",
            "plats",
            "komb",
            "tvilling",
            "trio"
          ]
        }
      ]
    }
  ],
  "version": 1777653323018,
  "newBettingSystem": true,
  "type": "vinnare"
}